plurk_oauth/__init__.py
plurk_oauth/api.py
plurk_oauth/oauth.py
plurk_oauth-0.9.2.data/scripts/get_own_profile.py
plurk_oauth-0.9.2.data/scripts/post_to_plurk.py
plurk_oauth-0.9.2.dist-info/DESCRIPTION.rst
plurk_oauth-0.9.2.dist-info/METADATA
plurk_oauth-0.9.2.dist-info/RECORD
plurk_oauth-0.9.2.dist-info/WHEEL
plurk_oauth-0.9.2.dist-info/metadata.json
plurk_oauth-0.9.2.dist-info/top_level.txt
