Metadata-Version: 1.1
Name: plurk-oauth
Version: 0.9.2
Summary: Plurk OAuth API
Home-page: https://github.com/clsung/plurk-oauth
Author: Cheng-Lung Sung
Author-email: clsung@gmail.com
License: UNKNOWN
Download-URL: http://pypi.python.org/pypi/plurk-oauth
Platform: UNKNOWN
